rich_typer/__init__.py
rich_typer/__main__.py
rich_typer/core.py
rich_typer/formatting.py
rich_typer/main.py
rich_typer/models.py
rich_typer/utils.py
rich_typer-0.1.7.dist-info/WHEEL
rich_typer-0.1.7.dist-info/METADATA
rich_typer-0.1.7.dist-info/RECORD
