Metadata-Version: 2.1
Name: rich-typer
Version: 0.1.7
Summary: more beautiful Typer
Home-page: https://github.com/Elinpf/rich_typer
Author: Elin
Author-email: 365433079@qq.com
Requires-Python: >=3.7,<4.0
Classifier: Programming Language :: Python :: 3
Classifier: Programming Language :: Python :: 3.7
Classifier: Programming Language :: Python :: 3.8
Classifier: Programming Language :: Python :: 3.9
Classifier: Programming Language :: Python :: 3.10
Requires-Dist: click (>=8.0.4,<9.0.0)
Requires-Dist: rich (>=11.2.0)
Requires-Dist: typer (>=0.4.2,<0.5.0)
Project-URL: Repository, https://github.com/Elinpf/rich_typer
